avici/__init__.py
avici/backbone.py
avici/buffer.py
avici/data.py
avici/definitions.py
avici/metrics.py
avici/model.py
avici/pretrain.py
avici/train.py
avici/assets/ecoli_transcriptional_network_regulonDB_6_7.tsv
avici/assets/yeast_transcriptional_network_Balaji2006.tsv
avici/config/examples/gene-ecoli.yaml
avici/config/examples/lin-gauss-heterosked.yaml
avici/config/examples/lin-gauss.yaml
avici/config/examples/lin-laplace-cauchy.yaml
avici/config/examples/rff-gauss-heterosked.yaml
avici/config/examples/rff-gauss.yaml
avici/config/examples/rff-laplace-cauchy.yaml
avici/config/train/neurips-grn.yaml
avici/config/train/neurips-linear.yaml
avici/config/train/neurips-rff.yaml
avici/config/train/scm-v0.yaml
avici/synthetic/__init__.py
avici/synthetic/abstract.py
avici/synthetic/distributions.py
avici/synthetic/gene.py
avici/synthetic/graph.py
avici/synthetic/linear.py
avici/synthetic/noise_scale.py
avici/synthetic/rff.py
avici/synthetic/utils.py
avici/synthetic/sergio/__init__.py
avici/synthetic/sergio/noise_config.yaml
avici/synthetic/sergio/sim.py
avici/utils/__init__.py
avici/utils/data.py
avici/utils/data_jax.py
avici/utils/example.py
avici/utils/graph.py
avici/utils/load.py
avici/utils/parse.py
avici/utils/plot.py
avici/utils/tf.py
avici/utils/version_control.py
avici-1.0.7.dist-info/LICENSE
avici-1.0.7.dist-info/METADATA
avici-1.0.7.dist-info/WHEEL
avici-1.0.7.dist-info/top_level.txt
avici-1.0.7.dist-info/RECORD
